deez/__init__.py
deez/__version__.py
deez/conf/__init__.py
deez/conf/default_settings.py
deez/conf/settings.py
deez/contrib/__init__.py
deez/contrib/serialization.py
deez/contrib/testing/__init__.py
deez/core/__init__.py
deez/core/api_gateway.py
deez/core/exception_handler.py
deez/core/router.py
deez/core/signals.py
deez/deez.py
deez/exceptions.py
deez/helpers.py
deez/logger.py
deez/middleware/__init__.py
deez/middleware/base.py
deez/middleware/base.pyi
deez/request.py
deez/resource.py
deez/response.py
deez/urls/__init__.py
deez/urls/parsers.py
deez/utils.py
deez-1.0.4.dist-info/METADATA
deez-1.0.4.dist-info/WHEEL
deez-1.0.4.dist-info/RECORD
