Metadata-Version: 2.1
Name: deez
Version: 1.0.4
Summary: A little library to simplify building small APIs on top of API Gateway and Lambda.
License: MIT
Author: Lemuel Boyce
Author-email: lemuel@prodperfect.com
Requires-Python: >=3.9,<4.0
Classifier: License :: OSI Approved :: MIT License
Classifier: Programming Language :: Python :: 3
Classifier: Programming Language :: Python :: 3.9
Classifier: Programming Language :: Python :: 3.10
Classifier: Programming Language :: Python :: 3.11
Requires-Dist: blinker (>=1.4)
